streetview/__init__.py
streetview/api.py
streetview/download.py
streetview/search.py
streetview/tools.py
streetview-0.0.16.dist-info/WHEEL
streetview-0.0.16.dist-info/METADATA
streetview-0.0.16.dist-info/RECORD
