Metadata-Version: 2.4
Name: streetview
Version: 0.0.16
Summary: Retrieve current and historical photos from Google Street View
Author: Adrian Letchford
Author-email: Adrian Letchford <me@dradrian.com>
License-Expression: MIT
Requires-Dist: httpx>=0.28.1
Requires-Dist: jupyter>=1.1.1
Requires-Dist: pillow>=11.3.0
Requires-Dist: pydantic>=2.11.7
Requires-Dist: requests>=2.32.4
Requires-Python: >=3.10
Project-URL: Homepage, https://github.com/robolyst/streetview
Project-URL: Issues, https://github.com/robolyst/streetview/issues
Project-URL: Source, https://github.com/robolyst/streetview
